optical_toolkit/__init__.py
optical_toolkit/__version__.py
optical_toolkit/analyze/__init__.py
optical_toolkit/analyze/analyze.py
optical_toolkit/analyze/functions/__init__.py
optical_toolkit/analyze/functions/all_embeddings.py
optical_toolkit/analyze/functions/summary_statistics.py
optical_toolkit/insight/__init__.py
optical_toolkit/insight/cnn_filters.py
optical_toolkit/insight/functions/__init__.py
optical_toolkit/insight/functions/filter_patterns.py
optical_toolkit/insight/functions/models_and_layers.py
optical_toolkit/insight/functions/stitched_image.py
optical_toolkit/utils/__init__.py
optical_toolkit/utils/deprocess_image.py
optical_toolkit/utils/min_max_normalize.py
optical_toolkit/utils/preprocess.py
optical_toolkit/utils/standardize.py
optical_toolkit/visualize/__init__.py
optical_toolkit/visualize/decorators/__init__.py
optical_toolkit/visualize/decorators/validate_plot_images.py
optical_toolkit/visualize/decorators/validate_summarize_images.py
optical_toolkit/visualize/embeddings.py
optical_toolkit/visualize/functions/__init__.py
optical_toolkit/visualize/functions/manifold_type.py
optical_toolkit/visualize/functions/manifolds.py
optical_toolkit/visualize/functions/visualize_utils.py
optical_toolkit/visualize/visualize_images.py
optical_toolkit-1.3.1.dist-info/METADATA
optical_toolkit-1.3.1.dist-info/WHEEL
optical_toolkit-1.3.1.dist-info/entry_points.txt
optical_toolkit-1.3.1.dist-info/licenses/LICENSE
optical_toolkit-1.3.1.dist-info/RECORD
