Metadata-Version: 2.4
Name: optical_toolkit
Version: 1.3.1
Summary: An API for streamlining unsupervised ML ops such as visualizations, clustering, CNN insights, etc.
License: MIT
License-File: LICENSE
Author: kenny
Author-email: 97374837+kankenny@users.noreply.github.com
Requires-Python: >=3.10,<4.0
Classifier: License :: OSI Approved :: MIT License
Classifier: Programming Language :: Python :: 3
Classifier: Programming Language :: Python :: 3.10
Classifier: Programming Language :: Python :: 3.11
Classifier: Programming Language :: Python :: 3.12
Classifier: Programming Language :: Python :: 3.13
Classifier: Programming Language :: Python :: 3.14
Requires-Dist: keras (==3.8)
Requires-Dist: matplotlib (>=3.10.1)
Requires-Dist: numpy (>=2.0.0)
Requires-Dist: pypdf (>=5.4.0,<6.0.0)
Requires-Dist: scikit-learn (>=1.6.1)
Requires-Dist: tensorflow (>=2.19.0,<3.0.0)
Requires-Dist: tqdm (>=4.67.1,<5.0.0)
